xnat/__init__.py
xnat/constants.py
xnat/convert_xsd.py
xnat/core.py
xnat/datatypes.py
xnat/exceptions.py
xnat/header.py
xnat/inspect.py
xnat/map.py
xnat/mixin.py
xnat/plugins.py
xnat/prearchive.py
xnat/search.py
xnat/services.py
xnat/session.py
xnat/type_hints.py
xnat/users.py
xnat/utils.py
xnat/version.py
xnat/cli/__init__.py
xnat/cli/download.py
xnat/cli/helpers.py
xnat/cli/importing.py
xnat/cli/listings.py
xnat/cli/prearchive.py
xnat/cli/rest.py
xnat/cli/scripts.py
xnat/cli/search.py
xnat/cli/upload.py
xnat/scripts/__init__.py
xnat/scripts/copy_project.py
xnat/scripts/data_integrity_check.py
xnat/scripts/delete_project.py
xnat/scripts/import_experiment_dir.py
xnat-0.7.2.dist-info/METADATA
xnat-0.7.2.dist-info/WHEEL
xnat-0.7.2.dist-info/entry_points.txt
xnat-0.7.2.dist-info/licenses/LICENSE
xnat-0.7.2.dist-info/RECORD
