Metadata-Version: 2.4
Name: xnat
Version: 0.7.2
Summary: An XNAT client that exposes the XNAT REST interface as python objects. Part of the interface is automatically generated based on the servers data model as defined by the xnat schema.
Project-URL: CI/CD, https://gitlab.com/radiology/infrastructure/xnatpy/-/pipelines
Project-URL: Changelog, https://xnat.readthedocs.io/en/latest/static/changelog.html
Project-URL: Documentation, https://xnat.readthedocs.io
Project-URL: Download, https://gitlab.com/radiology/infrastructure/xnatpy/-/archive/master/xnatpy-master.zip
Project-URL: Homepage, https://gitlab.com/radiology/infrastructure/xnatpy
Project-URL: Issues, https://gitlab.com/radiology/infrastructure/xnatpy/-/issues
Author-email: "H.C. Achterberg" <hakim.achterberg@gmail.com>
License:                                  Apache License
License-File: LICENSE
Classifier: Development Status :: 4 - Beta
Classifier: Intended Audience :: Developers
Classifier: Intended Audience :: Healthcare Industry
Classifier: Intended Audience :: Science/Research
Classifier: License :: OSI Approved :: Apache Software License
Classifier: Natural Language :: English
Classifier: Programming Language :: Python :: 3.8
Classifier: Programming Language :: Python :: 3.9
Classifier: Programming Language :: Python :: 3.10
Classifier: Programming Language :: Python :: 3.11
Classifier: Programming Language :: Python :: 3.12
Classifier: Programming Language :: Python :: 3.13
Classifier: Topic :: Scientific/Engineering :: Bio-Informatics
Classifier: Topic :: Scientific/Engineering :: Medical Science Apps.
Requires-Dist: click-option-group~=0.5.6
Requires-Dist: click~=8.0
Requires-Dist: importlib-metadata~=6.8
Requires-Dist: isodate~=0.6
Requires-Dist: progressbar2~=4.2
Requires-Dist: pydicom~=2.3
Requires-Dist: python-dateutil~=2.8.2
Requires-Dist: pyyaml~=6.0
Requires-Dist: requests~=2.30
